dev_toolbox/__init__.py
dev_toolbox/__main__.py
dev_toolbox/_types.py
dev_toolbox/_version.py
dev_toolbox/attrdict.py
dev_toolbox/browser_auth.py
dev_toolbox/multi_file.py
dev_toolbox/py.typed
dev_toolbox/pypi_api.py
dev_toolbox/table.py
dev_toolbox/utils.py
dev_toolbox/cli/__init__.py
dev_toolbox/cli/html_table.py
dev_toolbox/cli/ruff_doc.py
dev_toolbox/cli/tree.py
dev_toolbox/cli/version_bump.py
dev_toolbox/codegen/__init__.py
dev_toolbox/codegen/schema_parser.py
dev_toolbox/data_structures/__init__.py
dev_toolbox/data_structures/tree.py
dev_toolbox/decorators/__init__.py
dev_toolbox/decorators/timer.py
dev_toolbox/file_utils/__init__.py
dev_toolbox/file_utils/_json.py
dev_toolbox/http/__init__.py
dev_toolbox/http/_types.py
dev_toolbox/http/great_value.py
dev_toolbox/reflection_tools/__init__.py
dev_toolbox/reflection_tools/class_hierarchy.py
dev_toolbox-0.2.0.dist-info/METADATA
dev_toolbox-0.2.0.dist-info/WHEEL
dev_toolbox-0.2.0.dist-info/entry_points.txt
dev_toolbox-0.2.0.dist-info/licenses/LICENSE
dev_toolbox-0.2.0.dist-info/licenses/LICENSE.txt
dev_toolbox-0.2.0.dist-info/RECORD
